khl_card/__init__.py
khl_card/accessory.py
khl_card/builder.py
khl_card/card.py
khl_card/color.py
khl_card/modules.py
khl_card/types.py
KaiHeiLaCardBuilder-1.3.1.dist-info/LICENSE
KaiHeiLaCardBuilder-1.3.1.dist-info/METADATA
KaiHeiLaCardBuilder-1.3.1.dist-info/WHEEL
KaiHeiLaCardBuilder-1.3.1.dist-info/top_level.txt
KaiHeiLaCardBuilder-1.3.1.dist-info/RECORD
