Metadata-Version: 2.1
Name: KaiHeiLaCardBuilder
Version: 1.3.1
Summary: 一个构建开黑啦卡片的工具
Home-page: https://github.com/DancingSnow0517/KaiheilaCardBuilder
Author: DancingSnow
Author-email: 1121149616@qq.com
Project-URL: Bug Tracker, https://github.com/DancingSnow0517/KaiheilaCardBuilder/issues
Classifier: Programming Language :: Python :: 3
Classifier: License :: OSI Approved :: MIT License
Classifier: Operating System :: OS Independent
Requires-Python: >=3.6
License-File: LICENSE
